README.md
setup.py
nflxprofile/__init__.py
nflxprofile/cli.py
nflxprofile/flamegraph.py
nflxprofile/nflxprofile_pb2.py
nflxprofile.egg-info/PKG-INFO
nflxprofile.egg-info/SOURCES.txt
nflxprofile.egg-info/dependency_links.txt
nflxprofile.egg-info/entry_points.txt
nflxprofile.egg-info/requires.txt
nflxprofile.egg-info/top_level.txt
nflxprofile/convert/__init__.py
nflxprofile/convert/v8_cpuprofile.py
test/__init__.py
test/test_integ/__init__.py
test/test_integ/test_nodejs_package_processor.py
test/test_integ/test_nodejs_processor.py
test/test_unit/__init__.py
test/test_unit/test_java_stack_processor.py
test/test_unit/test_node_stack_processor.py